COPYING
DEPENDENCIES
MANIFEST.in
README.md
TODO
requirements.txt
setup.cfg
setup.py
cefdatabrowse/.databrowse-example
cefdatabrowse/__init__.py
cefdatabrowse/__init__.pyc
cefdatabrowse/cefdatabrowse.py
cefdatabrowse/cefdatabrowse_support.py
cefdatabrowse/cefdatabrowse_support.pyc
cefdatabrowse/__pycache__/__init__.cpython-37.pyc
cefdatabrowse/__pycache__/cefdatabrowse_support.cpython-37.pyc
cefdatabrowse/resources/Manual.pdf
cefdatabrowse/resources/back.gif
cefdatabrowse/resources/back.png
cefdatabrowse/resources/forward.gif
cefdatabrowse/resources/forward.png
cefdatabrowse/resources/icon256.png
cefdatabrowse/resources/reload.gif
cefdatabrowse/resources/reload.png
databrowse/__init__.py
databrowse/__init__.pyc
databrowse.egg-info/PKG-INFO
databrowse.egg-info/SOURCES.txt
databrowse.egg-info/dependency_links.txt
databrowse.egg-info/entry_points.txt
databrowse.egg-info/not-zip-safe
databrowse.egg-info/top_level.txt
databrowse/__pycache__/__init__.cpython-37.pyc
databrowse/lib/__init__.py
databrowse/lib/db_lib.py
databrowse/plugins/__init__.py
databrowse/plugins/__init__.pyc
databrowse/plugins/__pycache__/__init__.cpython-37.pyc
databrowse/plugins/db_PDF_viewer/__init__.py
databrowse/plugins/db_PDF_viewer/__init__.pyc
databrowse/plugins/db_PDF_viewer/db_PDF_viewer.py
databrowse/plugins/db_PDF_viewer/db_PDF_viewer.pyc
databrowse/plugins/db_PDF_viewer/dbs_preview_PDF.xml
databrowse/plugins/db_PDF_viewer/handlers.py
databrowse/plugins/db_PDF_viewer/handlers.pyc
databrowse/plugins/db_PDF_viewer/__pycache__/__init__.cpython-37.pyc
databrowse/plugins/db_PDF_viewer/__pycache__/handlers.cpython-37.pyc
databrowse/plugins/db_SolidWorks_viewer/__init__.py
databrowse/plugins/db_SolidWorks_viewer/__init__.pyc
databrowse/plugins/db_SolidWorks_viewer/db_SolidWorks_viewer.py
databrowse/plugins/db_SolidWorks_viewer/dbs_preview_SolidWorks_file.xml
databrowse/plugins/db_SolidWorks_viewer/handlers.py
databrowse/plugins/db_SolidWorks_viewer/handlers.pyc
databrowse/plugins/db_SolidWorks_viewer/__pycache__/__init__.cpython-37.pyc
databrowse/plugins/db_SolidWorks_viewer/__pycache__/handlers.cpython-37.pyc
databrowse/plugins/db_cad_model_viewer/__init__.py
