Metadata-Version: 2.1
Name: databrowse
Version: 0.8.4
Summary: An Extensible Data Management Platform
Home-page: http://limatix.org
Author: Tyler Lesthaeghe, Nathan Scheirer
Author-email: tylerl@iastate.edu, scheirer@iastate.edu
License: BSD-3
Keywords: databrowse data management
Platform: UNKNOWN
Classifier: Development Status :: 5 - Production/Stable
Classifier: Environment :: Web Environment
Classifier: Intended Audience :: Science/Research
Classifier: License :: OSI Approved :: GNU General Public License v3 or later (GPLv3+)
Classifier: Natural Language :: English
Classifier: Operating System :: OS Independent
Classifier: Programming Language :: Python :: 2
Classifier: Programming Language :: JavaScript
Classifier: Topic :: Internet :: WWW/HTTP :: WSGI :: Application
Classifier: Topic :: Internet :: WWW/HTTP :: WSGI :: Middleware
Classifier: Topic :: Scientific/Engineering :: Information Analysis
Classifier: Topic :: Software Development :: Libraries
Classifier: Topic :: Utilities
